lzhasyncemailsender/__init__.py
lzhasyncemailsender/aes.py
lzhasyncemailsender-1.1.dist-info/METADATA
lzhasyncemailsender-1.1.dist-info/WHEEL
lzhasyncemailsender-1.1.dist-info/top_level.txt
lzhasyncemailsender-1.1.dist-info/RECORD
