Metadata-Version: 2.4
Name: lzhasyncemailsender
Version: 1.1
Summary: 带有队列的异步邮件发送模块
Author-email: lzh <zhhtdm@hotmail.com>
License: MIT
Project-URL: Homepage, https://github.com/zhhtdm/async-email-sender
Project-URL: Repository, https://github.com/zhhtdm/async-email-sender
Requires-Python: >=3.10
Requires-Dist: aiosmtplib
Requires-Dist: lzhgetlogger
